easystyle/__init__.py
easystyle/easystyle.py
easystyle-0.4.dist-info/METADATA
easystyle-0.4.dist-info/RECORD
easystyle-0.4.dist-info/WHEEL
easystyle-0.4.dist-info/top_level.txt
