Metadata-Version: 2.1
Name: easystyle
Version: 0.4
Summary: A library that allows the user to quickly analyze data at a basic level without exporting to excel
Home-page: https://github.com/ethandrobbins/easystyle
Author: Ethan Robbins
Author-email: ethan.d.robbins@gmail.com
License: MIT
Download-URL: https://github.com/ethandrobbins/easystyle/archive/v_03.tar.gz
Keywords: STYLE,PANDAS,DATA
Platform: UNKNOWN
Classifier: Development Status :: 3 - Alpha
Classifier: Topic :: Software Development :: Build Tools
Classifier: License :: OSI Approved :: MIT License
Classifier: Programming Language :: Python :: 3.7
Requires-Dist: numpy
Requires-Dist: pandas
Requires-Dist: seaborn
